src/reg_ff.v
/*module reg_ff #(parameter DATA_WIDTH = 8) (
    input       clk,
    input       wr_en,
    input       [2:0] rs1, rs2, rd,
    input       [DATA_WIDTH-1:0] din,
    output      [DATA_WIDTH-1:0] r1, r2
);

reg [DATA_WIDTH-1:0] reg_file_arr [0:2];

integer i;
initial begin
    for (i = 0; i < 3; i = i + 1)
        reg_file_arr[i] = 0;
end

// register file write logic (synchronous)
always @(posedge clk) begin
    if (wr_en) reg_file_arr[rd] <= din;
end

// register file read logic (combinational)
assign r1 = ( rs1 != 0 ) ? reg_file_arr[rs1] : 0;
assign r2 = ( rs2 != 0 ) ? reg_file_arr[rs2] : 0;

endmodule

module reg_ff #(parameter DATA_WIDTH = 8) (
    input       clk,
    input       wr_en,
    input       [2:0] rs1, rs2, rd,
    input       [DATA_WIDTH-1:0] din,
    output      [DATA_WIDTH-1:0] r1, r2
);

reg [DATA_WIDTH-1:0] reg_file_arr [0:2];

// Initialize register file to avoid 'xxxxxxxx' issue in simulation
integer i;
initial begin
    for (i = 0; i < 3; i = i + 1)
        reg_file_arr[i] = 0;
end

// register file write logic (synchronous)
always @(posedge clk) begin
    if (wr_en) reg_file_arr[rd] <= din;
end

// register file read logic (combinational)
assign r1 = (rs1 != 0) ? reg_file_arr[rs1] : 0;
assign r2 = (rs2 != 0) ? reg_file_arr[rs2] : 0;

endmodule
*/

module reg_ff #(parameter DATA_WIDTH = 8) (clk, wrEn, rs1, rs2, rd, r1, r2, rst, dIn);
  input wire clk, wrEn, rst;
  input wire [2:0] rs1, rs2, rd;
  input wire [DATA_WIDTH-1:0] dIn;
  output wire [DATA_WIDTH-1:0] r1, r2;
  reg [DATA_WIDTH-1:0] reg_file [0:7];
  integer i = 0;
  initial begin
    for (i = 0; i < 8; i = i + 1) 
      begin
        reg_file[i] = 0;
      end
  end
  always @(posedge clk or posedge rst) begin
    if (rst) begin
      reg_file[0] <= 0;
      reg_file[1] <= 0;  // substitute with other values
      reg_file[2] <= 0;  // substitute with other values
      reg_file[3] <= 0;  // substitute with other values
      reg_file[4] <= 0;
      reg_file[5] <= 0;
      reg_file[6] <= 0;
      reg_file[7] <= 0;
    end else begin
      reg_file[rd] <= (wrEn && rd != 0) ? dIn : reg_file[rd];
    end
  end
/*
  always @(posedge clk) 
    reg_file[rd] <= (wrEn && rd != 0) ? dIn : reg_file[rd];
*/
  // register file read logic (combinational)
  assign r1 = (rs1 != 0 ) ? reg_file[rs1] : 0;
  assign r2 = (rs2 != 0 ) ? reg_file[rs2] : 0;
endmodule

testBench/tb_reg_ff.v
/*
module tb_reg_ff();
  reg clk_tb, wrEn_tb;
  reg [2:0] rd_tb;
  reg [2:0] rs1_tb;
  reg [2:0] rs2_tb;
  reg [7:0] dIn_tb;
  wire [7:0] r1_tb;
  wire [7:0] r2_tb;
  
  reg_ff dut (.clk(clk_tb), 
               .wr_en(wrEn_tb), 
               .rd(rd_tb), 
               .rs1(rs1_tb), 
               .rs2(rs2_tb), 
               .r1(r1_tb),
               .r2(r2_tb),
               .din(dIn_tb)
              );
  
  always begin
    clk_tb = 0;
    #5;
    clk_tb = 1;
    #5;
  end
  
  initial begin
    
    wrEn_tb = 1'b0;

    rs1_tb = 3'd0;
    rs2_tb = 3'd0;
    $monitor("Time = %0t, rs1 = %b, rs2 = %b, rd = %b, wrEn = %b, dataIn = %b, r1 = %b, r2 = %b", $time, rs1_tb, rs2_tb, rd_tb, wrEn_tb, dIn_tb, r1_tb, r2_tb);
    @(posedge clk_tb);
    wrEn_tb = 1'b1; rd_tb = 3'd0; dIn_tb = 8'hBC; 
    @(posedge clk_tb);
    wrEn_tb = 1'b1; rd_tb = 3'd1; dIn_tb = 8'hAB; 
    @(posedge clk_tb);
    wrEn_tb = 1'b1; rd_tb = 3'd2; dIn_tb = 8'h03; 
    @(posedge clk_tb);
    wrEn_tb = 1'b1; rd_tb = 3'd3; dIn_tb = 8'h5A; 
    @(posedge clk_tb);
    wrEn_tb = 1'b1; rd_tb = 3'd4; dIn_tb = 8'h6B; 
    @(posedge clk_tb);
    wrEn_tb = 1'b1; rd_tb = 3'd5; dIn_tb = 8'h3F; 
    @(posedge clk_tb);
    wrEn_tb = 1'b1; rd_tb = 3'd6; dIn_tb = 8'h7C; 
    @(posedge clk_tb);
    wrEn_tb = 1'b1; rd_tb = 3'd7; dIn_tb = 8'h2D; 
    @(posedge clk_tb);
    wrEn_tb = 1'b0;
    dIn_tb = 8'b0;
    rd_tb = 3'b0;
    #10;
    rs1_tb = 3'b001;
    rs2_tb = 3'b010;
    #10;
    rs1_tb = 3'b011;
    rs2_tb = 3'b100;
    #10;
    rs1_tb = 3'b101;
    rs2_tb = 3'b110;
    #10;
    rs1_tb = 3'b111;
    rs2_tb = 3'b000;
    #9;
    $finish;
  end
endmodule
*/
module tb_regFile();
  reg clk_tb, wrEn_tb, rst_tb;
  reg [2:0] rd_tb;
  reg [2:0] rs1_tb;
  reg [2:0] rs2_tb;
  reg [7:0] dIn_tb;
  wire [7:0] r1_tb;
  wire [7:0] r2_tb;
  
  reg_ff dut (.clk(clk_tb), 
               .wrEn(wrEn_tb), 
               .rd(rd_tb), 
               .rs1(rs1_tb), 
               .rs2(rs2_tb), 
               .r1(r1_tb),
               .r2(r2_tb),
               .dIn(dIn_tb),
               .rst(rst_tb)
              );
  
  always begin
    clk_tb = 0;
    #5;
    clk_tb = 1;
    #5;
  end
  
  initial begin
    $dumpfile("regFile.vcd");
    $dumpvars(0, tb_regFile);
    wrEn_tb = 1'b0;
    rst_tb = 1'b1;
    rs1_tb = 3'd6;
    rs2_tb = 3'd5;
    #1 rst_tb = 1'b0;
    @(posedge clk_tb);
    wrEn_tb = 1'b1; rd_tb = 3'd0; dIn_tb = 8'hA0; 
    @(posedge clk_tb);
    wrEn_tb = 1'b1; rd_tb = 3'd1; dIn_tb = 8'hF1; 
    @(posedge clk_tb);
    wrEn_tb = 1'b1; rd_tb = 3'd2; dIn_tb = 8'hFA; 
    @(posedge clk_tb);
    wrEn_tb = 1'b1; rd_tb = 3'd3; dIn_tb = 8'h03; 
    @(posedge clk_tb);
    wrEn_tb = 1'b1; rd_tb = 3'd4; dIn_tb = 8'hD3; 
    @(posedge clk_tb);
    wrEn_tb = 1'b1; rd_tb = 3'd5; dIn_tb = 8'hA5; 
    @(posedge clk_tb);
    wrEn_tb = 1'b1; rd_tb = 3'd6; dIn_tb = 8'h06; 
    @(posedge clk_tb);
    wrEn_tb = 1'b1; rd_tb = 3'd7; dIn_tb = 8'h07;  
    @(posedge clk_tb);
    wrEn_tb = 1'b0;
    dIn_tb = 8'b0;
    rd_tb = 3'b0;
    #10;
    rs1_tb = 3'b001;
    rs2_tb = 3'b010;
    #10;
    rs1_tb = 3'b011;
    rs2_tb = 3'b100;
    #10;
    rs1_tb = 3'b101;
    rs2_tb = 3'b110;
    #10;
    rs1_tb = 3'b111;
    rs2_tb = 3'b011;
    #10;
    rs1_tb = 3'b101;
    rs2_tb = 3'b010;
    #10;
    rs1_tb = 3'b111;
    rs2_tb = 3'b110;
    #10;
    #10;
    rst_tb = 1'b1;
    #1;
    rst_tb = 1'b0;
    #9;
    $finish;
  end
endmodule

waves/regFile.vcd
$date
	Wed Nov  6 12:56:21 2024
$end
$version
	Icarus Verilog
$end
$timescale
	1s
$end
$scope module tb_regFile $end
$var wire 8 ! r2_tb [7:0] $end
$var wire 8 " r1_tb [7:0] $end
$var reg 1 # clk_tb $end
$var reg 8 $ dIn_tb [7:0] $end
$var reg 3 % rd_tb [2:0] $end
$var reg 3 & rs1_tb [2:0] $end
$var reg 3 ' rs2_tb [2:0] $end
$var reg 1 ( rst_tb $end
$var reg 1 ) wrEn_tb $end
$scope module dut $end
$var wire 1 # clk $end
$var wire 8 * dIn [7:0] $end
$var wire 3 + rd [2:0] $end
$var wire 3 , rs1 [2:0] $end
$var wire 3 - rs2 [2:0] $end
$var wire 1 ( rst $end
$var wire 1 ) wrEn $end
$var wire 8 . r2 [7:0] $end
$var wire 8 / r1 [7:0] $end
$var integer 32 0 i [31:0] $end
$upscope $end
$upscope $end
$enddefinitions $end
#0
$dumpvars
b1000 0
b0 /
b0 .
b101 -
b110 ,
bx +
bx *
0)
1(
b101 '
b110 &
bx %
bx $
0#
b0 "
b0 !
$end
#1
0(
#5
b10100000 $
b10100000 *
b0 %
b0 +
1)
1#
#10
0#
#15
b11110001 $
b11110001 *
b1 %
b1 +
1#
#20
0#
#25
b11111010 $
b11111010 *
b10 %
b10 +
1#
#30
0#
#35
b11 $
b11 *
b11 %
b11 +
1#
#40
0#
#45
b11010011 $
b11010011 *
b100 %
b100 +
1#
#50
0#
#55
b10100101 !
b10100101 .
b10100101 $
b10100101 *
b101 %
b101 +
1#
#60
0#
#65
b110 "
b110 /
b110 $
b110 *
b110 %
b110 +
1#
#70
0#
#75
b111 $
b111 *
b111 %
b111 +
1#
#80
0#
#85
b0 %
b0 +
b0 $
b0 *
0)
1#
#90
0#
#95
b11111010 !
b11111010 .
b11110001 "
b11110001 /
1#
b10 '
b10 -
b1 &
b1 ,
#100
0#
#105
b11010011 !
b11010011 .
b11 "
b11 /
1#
b100 '
b100 -
b11 &
b11 ,
#110
0#
#115
b110 !
b110 .
b10100101 "
b10100101 /
1#
b110 '
b110 -
b101 &
b101 ,
#120
0#
#125
b11 !
b11 .
b111 "
b111 /
1#
b11 '
b11 -
b111 &
b111 ,
#130
0#
#135
b11111010 !
b11111010 .
b10100101 "
b10100101 /
1#
b10 '
b10 -
b101 &
b101 ,
#140
0#
#145
b110 !
b110 .
b111 "
b111 /
1#
b110 '
b110 -
b111 &
b111 ,
#150
0#
#155
1#
#160
0#
#165
b0 "
b0 /
b0 !
b0 .
1#
1(
#166
0(
